bdf2lvgl/__init__.py
bdf2lvgl/codegen/__init__.py
bdf2lvgl/codegen/c.py
bdf2lvgl/main.py
bdf2lvgl/parse.py
bdf2lvgl-0.2.1.dist-info/entry_points.txt
bdf2lvgl-0.2.1.dist-info/LICENSE
bdf2lvgl-0.2.1.dist-info/METADATA
bdf2lvgl-0.2.1.dist-info/WHEEL
bdf2lvgl-0.2.1.dist-info/RECORD
